petcmd/__init__.py
petcmd/argparser.py
petcmd/command.py
petcmd/commander.py
petcmd/exceptions.py
petcmd/interface.py
petcmd/single_command.py
petcmd/utils.py
petcmd/autocompletion/zsh.py
petcmd-1.0.5.dist-info/licenses/LICENSE
petcmd-1.0.5.dist-info/METADATA
petcmd-1.0.5.dist-info/WHEEL
petcmd-1.0.5.dist-info/top_level.txt
petcmd-1.0.5.dist-info/RECORD
