Metadata-Version: 2.4
Name: petcmd
Version: 1.0.5
Summary: Library for creating a command line tools
Author-email: Maks Vinnytskyi <ownerofforest@gmail.com>
Project-URL: Homepage, https://gitlab.com/Tullp/petcmd
Classifier: Programming Language :: Python :: 3.12
Classifier: License :: OSI Approved :: MIT License
Classifier: Operating System :: OS Independent
Requires-Python: >=3.12
License-File: LICENSE
Dynamic: license-file
